zope/container/__init__.py
zope/container/_compat.h
zope/container/_proxy.py
zope/container/_util.py
zope/container/_zope_container_contained.c
zope/container/_zope_container_contained.cpython-311-x86_64-linux-gnu.so
zope/container/btree.py
zope/container/configure.zcml
zope/container/constraints.py
zope/container/constraints.rst
zope/container/contained.py
zope/container/directory.py
zope/container/find.py
zope/container/folder.py
zope/container/i18n.py
zope/container/interfaces.py
zope/container/ordered.py
zope/container/sample.py
zope/container/size.py
zope/container/testing.py
zope/container/traversal.py
zope/container/tests/__init__.py
zope/container/tests/constraints_example.py
zope/container/tests/directory.rst
zope/container/tests/test_btree.py
zope/container/tests/test_compile_flags.py
zope/container/tests/test_constraints.py
zope/container/tests/test_contained.py
zope/container/tests/test_contained_zodb.py
zope/container/tests/test_containertraversable.py
zope/container/tests/test_containertraverser.py
zope/container/tests/test_dependencies.py
zope/container/tests/test_directory.py
zope/container/tests/test_find.py
zope/container/tests/test_folder.py
zope/container/tests/test_icontainer.py
zope/container/tests/test_ordered.py
zope/container/tests/test_size.py
zope_container-7.2.dist-info/METADATA
zope_container-7.2.dist-info/WHEEL
zope_container-7.2.dist-info/top_level.txt
zope_container-7.2.dist-info/RECORD
zope_container-7.2.dist-info/licenses/LICENSE.txt
