Metadata-Version: 2.4
Name: zope.container
Version: 7.2
Summary: Zope Container
Home-page: https://github.com/zopefoundation/zope.container
Author: Zope Foundation and Contributors
Author-email: zope-dev@zope.dev
License: ZPL-2.1
Project-URL: Documentation, https://zopecontainer.readthedocs.io
Project-URL: Issue Tracker, https://github.com/zopefoundation/zope.container/issues
Project-URL: Sources, https://github.com/zopefoundation/zope.container
Keywords: zope container
Classifier: Development Status :: 5 - Production/Stable
Classifier: Environment :: Web Environment
Classifier: Intended Audience :: Developers
Classifier: License :: OSI Approved :: Zope Public License
Classifier: Programming Language :: Python
Classifier: Programming Language :: Python :: 3
Classifier: Programming Language :: Python :: 3.10
Classifier: Programming Language :: Python :: 3.11
Classifier: Programming Language :: Python :: 3.12
Classifier: Programming Language :: Python :: 3.13
Classifier: Programming Language :: Python :: 3.14
Classifier: Programming Language :: Python :: Implementation :: CPython
Classifier: Programming Language :: Python :: Implementation :: PyPy
Classifier: Natural Language :: English
Classifier: Operating System :: OS Independent
Classifier: Topic :: Internet :: WWW/HTTP
Classifier: Framework :: Zope :: 3
Requires-Python: >=3.10
License-File: LICENSE.txt
Requires-Dist: BTrees
Requires-Dist: persistent>=4.1.0
Requires-Dist: zope.cachedescriptors
Requires-Dist: zope.component
Requires-Dist: zope.deferredimport
Requires-Dist: zope.dottedname
Requires-Dist: zope.event
Requires-Dist: zope.filerepresentation
Requires-Dist: zope.i18nmessageid
Requires-Dist: zope.interface
Requires-Dist: zope.lifecycleevent>=3.5.2
Requires-Dist: zope.location>=3.5.4
Requires-Dist: zope.proxy>=4.1.5
Requires-Dist: zope.publisher
Requires-Dist: zope.schema
Requires-Dist: zope.security
Requires-Dist: zope.size
Requires-Dist: zope.traversing>=4.0.0a1
Requires-Dist: setuptools
Provides-Extra: docs
Requires-Dist: Sphinx; extra == "docs"
Requires-Dist: repoze.sphinx.autointerface; extra == "docs"
Requires-Dist: sphinx_rtd_theme; extra == "docs"
Provides-Extra: test
Requires-Dist: zope.testing; extra == "test"
Requires-Dist: zope.testrunner>=6.4; extra == "test"
Requires-Dist: ZODB>=3.10; extra == "test"
Requires-Dist: zope.component[zcml]; extra == "test"
Requires-Dist: zope.configuration; extra == "test"
Requires-Dist: zope.security[zcml]>=4.0.0a3; extra == "test"
Provides-Extra: zcml
Requires-Dist: zope.component[zcml]; extra == "zcml"
Requires-Dist: zope.configuration; extra == "zcml"
Requires-Dist: zope.security[zcml]>=4.0.0a3; extra == "zcml"
Provides-Extra: zodb
Requires-Dist: ZODB>=3.10; extra == "zodb"
Dynamic: author
Dynamic: author-email
Dynamic: classifier
Dynamic: description
Dynamic: home-page
Dynamic: keywords
Dynamic: license
Dynamic: license-file
Dynamic: project-url
Dynamic: provides-extra
Dynamic: requires-dist
Dynamic: requires-python
Dynamic: summary
